CHANGELOG.md
LICENSE
MANIFEST.in
README.md
pyproject.toml
setup.cfg
setup.py
joringels/__init__.py
joringels/__main__.py
joringels.egg-info/PKG-INFO
joringels.egg-info/SOURCES.txt
joringels.egg-info/dependency_links.txt
joringels.egg-info/entry_points.txt
joringels.egg-info/requires.txt
joringels.egg-info/top_level.txt
joringels/logs/.gitkeep
joringels/resources/_joringels.yml
joringels/src/__init__.py
joringels/src/api_handler.py
joringels/src/arguments.py
joringels/src/auth_checker.py
joringels/src/contracts.py
joringels/src/encryption_dict_handler.py
joringels/src/encryption_handler.py
joringels/src/execute.py
joringels/src/flower.py
joringels/src/get_creds.py
joringels/src/get_soc.py
joringels/src/helpers.py
joringels/src/jorinde.py
joringels/src/joringels.py
joringels/src/joringels_server.py
joringels/src/logger.py
joringels/src/settings.py
joringels/src/actions/__init__.py
joringels/src/actions/chkey.py
joringels/src/actions/crypto.py
joringels/src/actions/dec.py
joringels/src/actions/dockerize.py
joringels/src/actions/fetch.py
joringels/src/actions/info.py
joringels/src/actions/invoke.py
joringels/src/actions/load.py
joringels/src/actions/serve.py
joringels/src/actions/show.py
joringels/src/actions/tempfile.py
joringels/src/actions/unittest.py
joringels/src/actions/unprotectedload.py
joringels/src/actions/upload.py
joringels/src/connectors/__init__.py
joringels/src/connectors/docker.py
joringels/src/connectors/scp.py
joringels/src/sources/__init__.py
joringels/src/sources/application.py
joringels/src/sources/kdbx.py
joringels/src/sources/kdbx_new.py
joringels/src/sources/kdbx_old.py
joringels/test/#test_kdbx.py
joringels/test/#test_kdbx_old.py
joringels/test/#test_load.py
joringels/test/__init__.py
joringels/test/test_actions.py
joringels/test/test_api_handler.py
joringels/test/test_encryption_dict_handler.py
joringels/test/test_encryption_handler.py
joringels/test/test_fetch.py
joringels/test/test_helpers.py
joringels/test/test_joringels.py
joringels/test/test_joringels_server.py
joringels/test/test_soc.py
joringels/test/test_tempfile.py
joringels/test/test_upload.py