Metadata-Version: 2.1
Name: joringels
Version: 0.2
Summary: btn secrets manager to be used wisely
Home-page: https://gitlab.com/larsmielke2/joringels
Author: Lars Mielke
Author-email: info@while-ai.org
License-File: LICENSE
Requires-Dist: colorama
Requires-Dist: pyyaml
Requires-Dist: pycryptodome
Requires-Dist: requests
Requires-Dist: tabulate
Requires-Dist: psutil
Requires-Dist: ipwhois
Requires-Dist: pykeepass
